arcula/__init__.py
arcula/arcula.py
arcula/bip44.py
arcula/constants.py
arcula/crypto.py
arcula/dhka.py
arcula/encode.py
arcula/hierarchy.py
arcula/t/__init__.py
arcula/t/test_arcula.py
arcula/t/test_bip44.py
arcula/t/test_crypto.py
arcula/t/test_dhka.py
arcula/t/test_encode.py
arcula-1.0.2.dist-info/LICENSE
arcula-1.0.2.dist-info/METADATA
arcula-1.0.2.dist-info/WHEEL
arcula-1.0.2.dist-info/top_level.txt
arcula-1.0.2.dist-info/RECORD
