Metadata-Version: 2.1
Name: arcula
Version: 1.0.2
Summary: Arcula: A Secure Hierarchical Deterministic Wallet
Home-page: https://github.com/aldur/Arcula
Author: Adriano Di Luzio
Author-email: adrianodl@hotmail.it
License: UNKNOWN
Platform: UNKNOWN
Classifier: Development Status :: 3 - Alpha
Classifier: Intended Audience :: Developers
Classifier: Intended Audience :: Financial and Insurance Industry
Classifier: Topic :: Software Development :: Build Tools
Classifier: Topic :: Office/Business :: Financial
Classifier: License :: OSI Approved :: MIT License
Classifier: Programming Language :: Python :: 3 :: Only
Classifier: Programming Language :: Python :: 3.7
Requires-Python: >=3.7
Requires-Dist: cryptography
Requires-Dist: ecdsa
Provides-Extra: dev
Requires-Dist: bitcash ; extra == 'dev'
Requires-Dist: ipdb ; extra == 'dev'
Requires-Dist: ipython ; extra == 'dev'
Requires-Dist: mnemonic ; extra == 'dev'
Requires-Dist: nose ; extra == 'dev'
Requires-Dist: requests ; extra == 'dev'
